dora_parquet_recorder/__init__.py
dora_parquet_recorder/__main__.py
dora_parquet_recorder/main.py
dora_parquet_recorder-0.1.0.dist-info/METADATA
dora_parquet_recorder-0.1.0.dist-info/WHEEL
dora_parquet_recorder-0.1.0.dist-info/entry_points.txt
dora_parquet_recorder-0.1.0.dist-info/top_level.txt
dora_parquet_recorder-0.1.0.dist-info/RECORD
