Metadata-Version: 2.4
Name: dora-parquet-recorder
Version: 0.1.0
Summary: A generic, zero-copy data recorder for dora.
Requires-Python: >=3.8
Requires-Dist: dora-rs
Requires-Dist: pyarrow
Requires-Dist: pandas
Requires-Dist: numpy
Requires-Dist: opencv-python
